[
  {
    "slug": "shiba-1",
    "name": "芝保育園",
    "type": "licensed",
    "area": "shiba-mita",
    "address": "港区芝5-18-1-101",
    "phone": "03-3455-4669",
    "hours": {
      "standard": "7:15-18:15",
      "extended": "18:15-22:00",
      "shortTime": null
    },
    "ageMin": 0,
    "ageMax": 5,
    "capacity": 164,
    "features": [
      "園庭あり",
      "延長保育",
      "障害児保育"
    ],
    "hasGarden": true,
    "nearestStation": "三田駅 徒歩5分 / 芝公園駅 徒歩7分",
    "website": "https://www.city.minato.tokyo.jp/kodomo/kodomo/kodomo/hoikuen/12/index.html",
    "lat": 35.6521,
    "lng": 139.7468,
    "operator": "港区",
    "notes": "芝地区の区立認可保育園。定員164名。"
  },
  {
    "slug": "shiba-2",
    "name": "神明保育園",
    "type": "licensed",
    "area": "shiba-mita",
    "address": "港区浜松町1-6-7",
    "phone": "03-5733-6822",
    "hours": {
      "standard": "7:15-18:15",
      "extended": "18:15-22:00",
      "shortTime": null
    },
    "ageMin": 0,
    "ageMax": 5,
    "capacity": 161,
    "features": [
      "園庭あり",
      "延長保育",
      "障害児保育"
    ],
    "hasGarden": true,
    "nearestStation": "浜松町駅 徒歩3分 / 大門駅 徒歩2分",
    "website": "https://www.nihonhoiku.co.jp/blog/shinmei/",
    "lat": 35.6564,
    "lng": 139.7548,
    "operator": "港区",
    "notes": "芝地区の区立認可保育園。定員161名。"
  },
  {
    "slug": "shiba-3",
    "name": "芝公園保育園",
    "type": "licensed",
    "area": "shiba-mita",
    "address": "港区芝公園2-7-3",
    "phone": "03-3438-0435",
    "hours": {
      "standard": "7:15-18:15",
      "extended": "18:15-20:15",
      "shortTime": null
    },
    "ageMin": 0,
    "ageMax": 5,
    "capacity": 150,
    "features": [
      "園庭あり",
      "延長保育",
      "障害児保育"
    ],
    "hasGarden": true,
    "nearestStation": "芝公園駅 徒歩3分 / 御成門駅 徒歩5分",
    "website": "https://www.city.minato.tokyo.jp/kodomo/kodomo/kodomo/hoikuen/13/index.html",
    "lat": 35.6554,
    "lng": 139.7464,
    "operator": "港区",
    "notes": "芝地区の区立認可保育園。定員150名。"
  },
  {
    "slug": "shiba-4",
    "name": "アスク芝公園保育園",
    "type": "licensed",
    "area": "shiba-mita",
    "address": "港区芝2-12-16",
    "phone": "03-5439-9398",
    "hours": {
      "standard": "7:15-18:15",
      "extended": "18:15-20:15",
      "shortTime": null
    },
    "ageMin": 0,
    "ageMax": 5,
    "capacity": 51,
    "features": [
      "延長保育",
      "食育"
    ],
    "hasGarden": false,
    "nearestStation": "芝公園駅 徒歩5分",
    "website": "https://www.nihonhoiku.co.jp/blog/shibakoen/",
    "lat": 35.6528,
    "lng": 139.7453,
    "operator": "株式会社日本保育サービス",
    "notes": "芝地区の私立認可保育園。定員51名。"
  },
  {
    "slug": "shiba-5",
    "name": "太陽の子三田保育園",
    "type": "licensed",
    "area": "shiba-mita",
    "address": "港区三田1-2-18",
    "phone": "03-5439-6390",
    "hours": {
      "standard": "7:15-18:15",
      "extended": "18:15-20:15",
      "shortTime": null
    },
    "ageMin": 0,
    "ageMax": 5,
    "capacity": 69,
    "features": [
      "延長保育",
      "食育"
    ],
    "hasGarden": false,
    "nearestStation": "赤羽橋駅 徒歩5分 / 麻布十番駅 徒歩8分",
    "website": "https://www.kidslife-nursery.com/facility/tokyo/minato/mita1/",
    "lat": 35.65,
    "lng": 139.7432,
    "operator": "HITOWAキッズライフ株式会社",
    "notes": "芝地区の私立認可保育園。定員69名。"
  },
  {
    "slug": "shiba-6",
    "name": "アイグラン保育園赤羽橋",
    "type": "licensed",
    "area": "shiba-mita",
    "address": "港区三田1-3-31",
    "phone": "03-6453-9325",
    "hours": {
      "standard": "7:15-18:15",
      "extended": "18:15-20:15",
      "shortTime": null
    },
    "ageMin": 0,
    "ageMax": 5,
    "capacity": 60,
    "features": [
      "延長保育",
      "食育"
    ],
    "hasGarden": false,
    "nearestStation": "赤羽橋駅 徒歩3分",
    "website": "https://aigran.co.jp/nursery/ninka/nursery-357/",
    "lat": 35.6505,
    "lng": 139.744,
    "operator": "株式会社アイグラン",
    "notes": "芝地区の私立認可保育園。定員60名。"
  },
  {
    "slug": "shiba-7",
    "name": "こころ新橋保育園",
    "type": "licensed",
    "area": "shiba-mita",
    "address": "港区新橋6-4-3",
    "phone": "03-6432-0941",
    "hours": {
      "standard": "7:15-18:15",
      "extended": "18:15-20:15",
      "shortTime": null
    },
    "ageMin": 0,
    "ageMax": 5,
    "capacity": 48,
    "features": [
      "延長保育",
      "食育"
    ],
    "hasGarden": false,
    "nearestStation": "御成門駅 徒歩5分 / 新橋駅 徒歩8分",
    "website": "https://www.taiyo.ed.jp/kokoro-shinbashi/",
    "lat": 35.6586,
    "lng": 139.7504,
    "operator": "株式会社こころケアプラン",
    "notes": "芝地区の私立認可保育園。定員48名。"
  },
  {
    "slug": "shiba-8",
    "name": "グローバルキッズ虎ノ門保育園",
    "type": "licensed",
    "area": "shiba-mita",
    "address": "港区虎ノ門3-19-13",
    "phone": "03-5473-7668",
    "hours": {
      "standard": "7:15-18:15",
      "extended": "18:15-20:15",
      "shortTime": null
    },
    "ageMin": 0,
    "ageMax": 5,
    "capacity": 56,
    "features": [
      "延長保育",
      "食育"
    ],
    "hasGarden": false,
    "nearestStation": "神谷町駅 徒歩3分",
    "website": "https://www.gkids.co.jp/facilities/nursery_061.html",
    "lat": 35.661,
    "lng": 139.748,
    "operator": "株式会社グローバルキッズ",
    "notes": "芝地区の私立認可保育園。定員56名。"
  },
  {
    "slug": "shiba-9",
    "name": "小鳩ナーサリースクール浜離宮",
    "type": "licensed",
    "area": "shiba-mita",
    "address": "港区浜松町1-3-1",
    "phone": "03-6432-0123",
    "hours": {
      "standard": "7:15-18:15",
      "extended": "18:15-20:15",
      "shortTime": null
    },
    "ageMin": 0,
    "ageMax": 5,
    "capacity": 41,
    "features": [
      "延長保育",
      "食育"
    ],
    "hasGarden": false,
    "nearestStation": "浜松町駅 徒歩5分 / 竹芝駅 徒歩3分",
    "website": "https://www.kobato.net/hamarikyu/",
    "lat": 35.6572,
    "lng": 139.756,
    "operator": "社会福祉法人小鳩会",
    "notes": "芝地区の私立認可保育園。定員41名。"
  },
  {
    "slug": "shiba-10",
    "name": "ニチイキッズ芝公園保育園",
    "type": "licensed",
    "area": "shiba-mita",
    "address": "港区芝2-1-27",
    "phone": "03-5765-5075",
    "hours": {
      "standard": "7:15-18:15",
      "extended": "18:15-20:15",
      "shortTime": null
    },
    "ageMin": 0,
    "ageMax": 5,
    "capacity": 45,
    "features": [
      "延長保育",
      "食育"
    ],
    "hasGarden": false,
    "nearestStation": "芝公園駅 徒歩3分",
    "website": "https://www.nichiikids.net/nursery/shibakouen/",
    "lat": 35.653,
    "lng": 139.7445,
    "operator": "株式会社ニチイ学館",
    "notes": "芝地区の私立認可保育園。定員45名。"
  },
  {
    "slug": "shiba-11",
    "name": "にじいろ保育園竹芝",
    "type": "licensed",
    "area": "shiba-mita",
    "address": "港区海岸1-13-15",
    "phone": "03-6381-5195",
    "hours": {
      "standard": "7:15-18:15",
      "extended": "18:15-20:15",
      "shortTime": null
    },
    "ageMin": 0,
    "ageMax": 5,
    "capacity": 32,
    "features": [
      "延長保育",
      "食育"
    ],
    "hasGarden": false,
    "nearestStation": "竹芝駅 徒歩3分 / 浜松町駅 徒歩8分",
    "website": "https://www.like-kd.co.jp/establishment/nijiiro/HPtakeshiba",
    "lat": 35.6537,
    "lng": 139.7585,
    "operator": "ライクキッズ株式会社",
    "notes": "芝地区の私立認可保育園。定員32名。"
  },
  {
    "slug": "shiba-12",
    "name": "にじいろ保育園新橋",
    "type": "licensed",
    "area": "shiba-mita",
    "address": "港区新橋6-11-13",
    "phone": "03-6432-0540",
    "hours": {
      "standard": "7:15-18:15",
      "extended": "18:15-20:15",
      "shortTime": null
    },
    "ageMin": 0,
    "ageMax": 5,
    "capacity": 36,
    "features": [
      "延長保育",
      "食育"
    ],
    "hasGarden": false,
    "nearestStation": "御成門駅 徒歩3分 / 新橋駅 徒歩7分",
    "website": "https://www.like-kd.co.jp/establishment/nijiiro/HPshinbashi",
    "lat": 35.659,
    "lng": 139.7498,
    "operator": "ライクキッズ株式会社",
    "notes": "芝地区の私立認可保育園。定員36名。"
  },
  {
    "slug": "shiba-13",
    "name": "汐留サーノ保育園",
    "type": "licensed",
    "area": "shiba-mita",
    "address": "港区浜松町1-1-11",
    "phone": "03-6452-8944",
    "hours": {
      "standard": "7:15-18:15",
      "extended": "18:15-20:15",
      "shortTime": null
    },
    "ageMin": 0,
    "ageMax": 5,
    "capacity": 80,
    "features": [
      "延長保育",
      "食育"
    ],
    "hasGarden": false,
    "nearestStation": "浜松町駅 徒歩2分 / 汐留駅 徒歩5分",
    "website": "https://shiodome-kids.com/",
    "lat": 35.6578,
    "lng": 139.7562,
    "operator": "社会福祉法人聖母愛真会",
    "notes": "芝地区の私立認可保育園。定員80名。"
  },
  {
    "slug": "azabu-14",
    "name": "南麻布保育園",
    "type": "licensed",
    "area": "azabu",
    "address": "港区南麻布4-2-29-101",
    "phone": "03-3442-8068",
    "hours": {
      "standard": "7:15-18:15",
      "extended": "18:15-20:15",
      "shortTime": null
    },
    "ageMin": 0,
    "ageMax": 5,
    "capacity": 100,
    "features": [
      "園庭あり",
      "延長保育",
      "障害児保育"
    ],
    "hasGarden": true,
    "nearestStation": "広尾駅 徒歩5分",
    "website": "https://www.city.minato.tokyo.jp/kodomo/kodomo/kodomo/hoikuen/10/index.html",
    "lat": 35.6502,
    "lng": 139.723,
    "operator": "港区",
    "notes": "麻布地区の区立認可保育園。定員100名。"
  },
  {
    "slug": "azabu-15",
    "name": "本村保育園",
    "type": "licensed",
    "area": "azabu",
    "address": "港区南麻布4-6-7",
    "phone": "03-3444-2385",
    "hours": {
      "standard": "7:15-18:15",
      "extended": "18:15-20:15",
      "shortTime": null
    },
    "ageMin": 0,
    "ageMax": 5,
    "capacity": 106,
    "features": [
      "園庭あり",
      "延長保育",
      "障害児保育"
    ],
    "hasGarden": true,
    "nearestStation": "広尾駅 徒歩5分",
    "website": "https://www.city.minato.tokyo.jp/kodomo/kodomo/kodomo/hoikuen/05/index.html",
    "lat": 35.6498,
    "lng": 139.722,
    "operator": "港区",
    "notes": "麻布地区の区立認可保育園。定員106名。"
  },
  {
    "slug": "azabu-16",
    "name": "西麻布保育園",
    "type": "licensed",
    "area": "azabu",
    "address": "港区西麻布2-13-3",
    "phone": "03-3409-4924",
    "hours": {
      "standard": "7:15-18:15",
      "extended": "18:15-20:15",
      "shortTime": null
    },
    "ageMin": 0,
    "ageMax": 5,
    "capacity": 125,
    "features": [
      "園庭あり",
      "延長保育",
      "障害児保育"
    ],
    "hasGarden": true,
    "nearestStation": "六本木駅 徒歩10分 / 乃木坂駅 徒歩8分",
    "website": "https://www.city.minato.tokyo.jp/kodomo/kodomo/kodomo/hoikuen/11/index.html",
    "lat": 35.6594,
    "lng": 139.7235,
    "operator": "港区",
    "notes": "麻布地区の区立認可保育園。定員125名。"
  },
  {
    "slug": "azabu-17",
    "name": "麻布保育園",
    "type": "licensed",
    "area": "azabu",
    "address": "港区六本木5-16-46",
    "phone": "03-5545-7135",
    "hours": {
      "standard": "7:15-18:15",
      "extended": "18:15-20:15",
      "shortTime": null
    },
    "ageMin": 0,
    "ageMax": 5,
    "capacity": 144,
    "features": [
      "園庭あり",
      "延長保育",
      "障害児保育"
    ],
    "hasGarden": true,
    "nearestStation": "六本木駅 徒歩5分 / 麻布十番駅 徒歩8分",
    "website": "https://www.city.minato.tokyo.jp/kodomo/kodomo/kodomo/hoikuen/03/index.html",
    "lat": 35.658,
    "lng": 139.731,
    "operator": "港区",
    "notes": "麻布地区の区立認可保育園。定員144名。"
  },
  {
    "slug": "azabu-18",
    "name": "飯倉保育園",
    "type": "licensed",
    "area": "azabu",
    "address": "港区東麻布1-21-2",
    "phone": "03-3583-1786",
    "hours": {
      "standard": "7:15-18:15",
      "extended": "18:15-20:15",
      "shortTime": null
    },
    "ageMin": 0,
    "ageMax": 5,
    "capacity": 131,
    "features": [
      "園庭あり",
      "延長保育",
      "障害児保育"
    ],
    "hasGarden": true,
    "nearestStation": "赤羽橋駅 徒歩5分 / 麻布十番駅 徒歩5分",
    "website": "https://www.city.minato.tokyo.jp/kodomo/kodomo/kodomo/hoikuen/06/index.html",
    "lat": 35.656,
    "lng": 139.739,
    "operator": "港区",
    "notes": "麻布地区の区立認可保育園。定員131名。"
  },
  {
    "slug": "azabu-19",
    "name": "東麻布保育園",
    "type": "licensed",
    "area": "azabu",
    "address": "港区東麻布2-1-1",
    "phone": "03-3584-3811",
    "hours": {
      "standard": "7:15-18:15",
      "extended": "18:15-22:00",
      "shortTime": null
    },
    "ageMin": 0,
    "ageMax": 5,
    "capacity": 160,
    "features": [
      "園庭あり",
      "延長保育",
      "障害児保育"
    ],
    "hasGarden": true,
    "nearestStation": "赤羽橋駅 徒歩3分",
    "website": "https://minato-hah.com/",
    "lat": 35.6565,
    "lng": 139.7378,
    "operator": "港区",
    "notes": "麻布地区の区立認可保育園。定員160名。"
  },
  {
    "slug": "azabu-20",
    "name": "元麻布保育園",
    "type": "licensed",
    "area": "azabu",
    "address": "港区元麻布2-14-12",
    "phone": "03-5422-7338",
    "hours": {
      "standard": "7:15-18:15",
      "extended": "18:15-22:00",
      "shortTime": null
    },
    "ageMin": 0,
    "ageMax": 5,
    "capacity": 168,
    "features": [
      "園庭あり",
      "延長保育",
      "障害児保育"
    ],
    "hasGarden": true,
    "nearestStation": "麻布十番駅 徒歩8分 / 広尾駅 徒歩10分",
    "website": "https://www.city.minato.tokyo.jp/kodomo/kodomo/kodomo/hoikuen/26/index.html",
    "lat": 35.6555,
    "lng": 139.728,
    "operator": "港区",
    "notes": "麻布地区の区立認可保育園。定員168名。"
  },
  {
    "slug": "azabu-21",
    "name": "まなびの森保育園麻布",
    "type": "licensed",
    "area": "azabu",
    "address": "港区南麻布1-8-11",
    "phone": "03-3455-3066",
    "hours": {
      "standard": "7:15-18:15",
      "extended": "18:15-20:15",
      "shortTime": null
    },
    "ageMin": 0,
    "ageMax": 5,
    "capacity": 60,
    "features": [
      "延長保育",
      "食育"
    ],
    "hasGarden": false,
    "nearestStation": "麻布十番駅 徒歩5分",
    "website": "http://kodomonomori.co.jp/az/",
    "lat": 35.649,
    "lng": 139.733,
    "operator": "株式会社こどもの森",
    "notes": "麻布地区の私立認可保育園。定員60名。"
  },
  {
    "slug": "azabu-22",
    "name": "アイグラン保育園南麻布",
    "type": "licensed",
    "area": "azabu",
    "address": "港区南麻布2-11-10",
    "phone": "03-6453-7970",
    "hours": {
      "standard": "7:15-18:15",
      "extended": "18:15-20:15",
      "shortTime": null
    },
    "ageMin": 0,
    "ageMax": 5,
    "capacity": 98,
    "features": [
      "延長保育",
      "食育"
    ],
    "hasGarden": false,
    "nearestStation": "白金高輪駅 徒歩10分 / 麻布十番駅 徒歩8分",
    "website": "https://aigran.co.jp/nursery/ninka/nursery-359/",
    "lat": 35.6485,
    "lng": 139.729,
    "operator": "株式会社アイグラン",
    "notes": "麻布地区の私立認可保育園。定員98名。"
  },
  {
    "slug": "azabu-23",
    "name": "太陽の子南麻布保育園",
    "type": "licensed",
    "area": "azabu",
    "address": "港区南麻布4-11-30",
    "phone": "03-5488-8070",
    "hours": {
      "standard": "7:15-18:15",
      "extended": "18:15-20:15",
      "shortTime": null
    },
    "ageMin": 0,
    "ageMax": 5,
    "capacity": 69,
    "features": [
      "延長保育",
      "食育"
    ],
    "hasGarden": false,
    "nearestStation": "広尾駅 徒歩3分",
    "website": "https://www.kidslife-nursery.com/facility/tokyo/minato/minamiazabu/",
    "lat": 35.6492,
    "lng": 139.7218,
    "operator": "HITOWAキッズライフ株式会社",
    "notes": "麻布地区の私立認可保育園。定員69名。"
  },
  {
    "slug": "azabu-24",
    "name": "アイグラン保育園元麻布",
    "type": "licensed",
    "area": "azabu",
    "address": "港区元麻布3-2-19",
    "phone": "03-6447-1871",
    "hours": {
      "standard": "7:15-18:15",
      "extended": "18:15-20:15",
      "shortTime": null
    },
    "ageMin": 0,
    "ageMax": 5,
    "capacity": 60,
    "features": [
      "延長保育",
      "食育"
    ],
    "hasGarden": false,
    "nearestStation": "麻布十番駅 徒歩7分 / 六本木駅 徒歩10分",
    "website": "https://aigran.co.jp/nursery/ninka/nursery-358/",
    "lat": 35.6558,
    "lng": 139.727,
    "operator": "株式会社アイグラン",
    "notes": "麻布地区の私立認可保育園。定員60名。"
  },
  {
    "slug": "azabu-25",
    "name": "まちの保育園六本木",
    "type": "licensed",
    "area": "azabu",
    "address": "港区六本木1-9-10",
    "phone": "03-6441-2478",
    "hours": {
      "standard": "7:15-18:15",
      "extended": "18:15-20:30",
      "shortTime": null
    },
    "ageMin": 0,
    "ageMax": 5,
    "capacity": 38,
    "features": [
      "延長保育",
      "食育"
    ],
    "hasGarden": false,
    "nearestStation": "六本木一丁目駅 徒歩2分",
    "website": "https://machihoiku.jp/roppongi/",
    "lat": 35.663,
    "lng": 139.739,
    "operator": "ナチュラルスマイルジャパン株式会社",
    "notes": "麻布地区の私立認可保育園。定員38名。"
  },
  {
    "slug": "azabu-26",
    "name": "コスモス西麻布保育園",
    "type": "licensed",
    "area": "azabu",
    "address": "港区西麻布2-2-2",
    "phone": "03-6427-3733",
    "hours": {
      "standard": "7:15-18:15",
      "extended": "18:15-20:15",
      "shortTime": null
    },
    "ageMin": 0,
    "ageMax": 5,
    "capacity": 50,
    "features": [
      "延長保育",
      "食育"
    ],
    "hasGarden": false,
    "nearestStation": "六本木駅 徒歩8分",
    "website": "https://cosmosnishiazabu.wixsite.com/cosmos",
    "lat": 35.66,
    "lng": 139.725,
    "operator": "株式会社コスモス",
    "notes": "麻布地区の私立認可保育園。定員50名。"
  },
  {
    "slug": "azabu-27",
    "name": "麻布十番ちとせ保育園",
    "type": "licensed",
    "area": "azabu",
    "address": "港区麻布十番1-3-2",
    "phone": "03-3586-1058",
    "hours": {
      "standard": "7:15-18:15",
      "extended": "18:15-20:15",
      "shortTime": null
    },
    "ageMin": 0,
    "ageMax": 5,
    "capacity": 60,
    "features": [
      "延長保育",
      "食育"
    ],
    "hasGarden": false,
    "nearestStation": "麻布十番駅 徒歩2分",
    "website": "https://www.chitosek.or.jp/preschools/azabujuban",
    "lat": 35.6545,
    "lng": 139.7365,
    "operator": "社会福祉法人ちとせ交友会",
    "notes": "麻布地区の私立認可保育園。定員60名。"
  },
  {
    "slug": "azabu-28",
    "name": "sakura保育園六本木",
    "type": "licensed",
    "area": "azabu",
    "address": "港区六本木4-5-11",
    "phone": "03-6434-5011",
    "hours": {
      "standard": "7:15-18:15",
      "extended": "18:15-20:30",
      "shortTime": null
    },
    "ageMin": 0,
    "ageMax": 5,
    "capacity": 52,
    "features": [
      "延長保育",
      "食育"
    ],
    "hasGarden": false,
    "nearestStation": "六本木駅 徒歩3分",
    "website": "https://sakurakids.net/",
    "lat": 35.6625,
    "lng": 139.732,
    "operator": "株式会社さくらさくみらい",
    "notes": "麻布地区の私立認可保育園。定員52名。"
  },
  {
    "slug": "akasaka-29",
    "name": "赤坂保育園",
    "type": "licensed",
    "area": "akasaka-aoyama",
    "address": "港区赤坂5-5-26-101",
    "phone": "03-3583-2156",
    "hours": {
      "standard": "7:15-18:15",
      "extended": "18:15-20:15",
      "shortTime": null
    },
    "ageMin": 0,
    "ageMax": 5,
    "capacity": 99,
    "features": [
      "園庭あり",
      "延長保育",
      "障害児保育"
    ],
    "hasGarden": true,
    "nearestStation": "赤坂駅 徒歩3分 / 赤坂見附駅 徒歩5分",
    "website": "https://www.city.minato.tokyo.jp/kodomo/kodomo/kodomo/hoikuen/01/index.html",
    "lat": 35.672,
    "lng": 139.734,
    "operator": "港区",
    "notes": "赤坂地区の区立認可保育園。定員99名。"
  },
  {
    "slug": "akasaka-30",
    "name": "南青山保育園",
    "type": "licensed",
    "area": "akasaka-aoyama",
    "address": "港区南青山1-3-15",
    "phone": "03-3401-1650",
    "hours": {
      "standard": "7:15-18:15",
      "extended": "18:15-20:15",
      "shortTime": null
    },
    "ageMin": 0,
    "ageMax": 5,
    "capacity": 136,
    "features": [
      "園庭あり",
      "延長保育",
      "障害児保育"
    ],
    "hasGarden": true,
    "nearestStation": "青山一丁目駅 徒歩3分 / 乃木坂駅 徒歩5分",
    "website": "https://www.city.minato.tokyo.jp/kodomo/kodomo/kodomo/hoikuen/09/index.html",
    "lat": 35.67,
    "lng": 139.721,
    "operator": "港区",
    "notes": "赤坂地区の区立認可保育園。定員136名。"
  },
  {
    "slug": "akasaka-31",
    "name": "青山保育園",
    "type": "licensed",
    "area": "akasaka-aoyama",
    "address": "港区北青山3-4-1-101",
    "phone": "03-3401-1723",
    "hours": {
      "standard": "7:15-18:15",
      "extended": "18:15-20:15",
      "shortTime": null
    },
    "ageMin": 0,
    "ageMax": 5,
    "capacity": 128,
    "features": [
      "園庭あり",
      "延長保育",
      "障害児保育"
    ],
    "hasGarden": true,
    "nearestStation": "表参道駅 徒歩3分",
    "website": "https://www.city.minato.tokyo.jp/kodomo/kodomo/kodomo/hoikuen/02/index.html",
    "lat": 35.6653,
    "lng": 139.7129,
    "operator": "港区",
    "notes": "赤坂地区の区立認可保育園。定員128名。"
  },
  {
    "slug": "akasaka-32",
    "name": "赤坂ちとせ保育園",
    "type": "licensed",
    "area": "akasaka-aoyama",
    "address": "港区赤坂4-7-15",
    "phone": "03-6459-1012",
    "hours": {
      "standard": "7:15-18:15",
      "extended": "18:15-20:15",
      "shortTime": null
    },
    "ageMin": 0,
    "ageMax": 5,
    "capacity": 50,
    "features": [
      "延長保育",
      "食育"
    ],
    "hasGarden": false,
    "nearestStation": "赤坂見附駅 徒歩3分",
    "website": "https://www.chitosek.or.jp/preschools/akasaka",
    "lat": 35.673,
    "lng": 139.732,
    "operator": "社会福祉法人ちとせ交友会",
    "notes": "赤坂地区の私立認可保育園。定員50名。"
  },
  {
    "slug": "akasaka-33",
    "name": "太陽の子赤坂保育園",
    "type": "licensed",
    "area": "akasaka-aoyama",
    "address": "港区赤坂8-12-16",
    "phone": "03-6434-9431",
    "hours": {
      "standard": "7:15-18:15",
      "extended": "18:15-20:15",
      "shortTime": null
    },
    "ageMin": 0,
    "ageMax": 5,
    "capacity": 60,
    "features": [
      "延長保育",
      "食育"
    ],
    "hasGarden": false,
    "nearestStation": "乃木坂駅 徒歩3分 / 青山一丁目駅 徒歩5分",
    "website": "https://www.kidslife-nursery.com/facility/tokyo/minato/akasaka/",
    "lat": 35.671,
    "lng": 139.726,
    "operator": "HITOWAキッズライフ株式会社",
    "notes": "赤坂地区の私立認可保育園。定員60名。"
  },
  {
    "slug": "akasaka-34",
    "name": "アイグラン保育園青山一丁目",
    "type": "licensed",
    "area": "akasaka-aoyama",
    "address": "港区南青山1-3-1",
    "phone": "03-6459-2860",
    "hours": {
      "standard": "7:15-18:15",
      "extended": "18:15-20:15",
      "shortTime": null
    },
    "ageMin": 0,
    "ageMax": 5,
    "capacity": 60,
    "features": [
      "延長保育",
      "食育"
    ],
    "hasGarden": false,
    "nearestStation": "青山一丁目駅 徒歩1分",
    "website": "https://aigran.co.jp/nursery/ninka/nursery-3584/",
    "lat": 35.6698,
    "lng": 139.7215,
    "operator": "株式会社アイグラン",
    "notes": "赤坂地区の私立認可保育園。定員60名。"
  },
  {
    "slug": "akasaka-35",
    "name": "赤坂山王保育園",
    "type": "licensed",
    "area": "akasaka-aoyama",
    "address": "港区赤坂4-1-26",
    "phone": "03-5114-5605",
    "hours": {
      "standard": "7:15-18:15",
      "extended": "18:15-20:15",
      "shortTime": null
    },
    "ageMin": 0,
    "ageMax": 5,
    "capacity": 121,
    "features": [
      "延長保育",
      "食育"
    ],
    "hasGarden": false,
    "nearestStation": "赤坂見附駅 徒歩5分 / 溜池山王駅 徒歩5分",
    "website": "https://hoyukai.iuhw.ac.jp/akasakasanno-h/",
    "lat": 35.674,
    "lng": 139.737,
    "operator": "社会福祉法人三祉会",
    "notes": "赤坂地区の私立認可保育園。定員121名。"
  },
  {
    "slug": "akasaka-36",
    "name": "小学館アカデミー南青山保育園",
    "type": "licensed",
    "area": "akasaka-aoyama",
    "address": "港区南青山4-15-8",
    "phone": "03-5770-1512",
    "hours": {
      "standard": "7:15-18:15",
      "extended": "18:15-20:15",
      "shortTime": null
    },
    "ageMin": 0,
    "ageMax": 5,
    "capacity": 39,
    "features": [
      "延長保育",
      "食育"
    ],
    "hasGarden": false,
    "nearestStation": "表参道駅 徒歩5分",
    "website": "https://hoiku.shopro.co.jp/hoiku/shisetsu/minamiaoyama/",
    "lat": 35.665,
    "lng": 139.715,
    "operator": "株式会社小学館集英社プロダクション",
    "notes": "赤坂地区の私立認可保育園。定員39名。"
  },
  {
    "slug": "takanawa-37",
    "name": "伊皿子坂保育園",
    "type": "licensed",
    "area": "takanawa-shirokane",
    "address": "港区三田4-19-30",
    "phone": "03-3444-7601",
    "hours": {
      "standard": "7:15-18:15",
      "extended": "18:15-20:15",
      "shortTime": null
    },
    "ageMin": 0,
    "ageMax": 5,
    "capacity": 149,
    "features": [
      "園庭あり",
      "延長保育",
      "障害児保育"
    ],
    "hasGarden": true,
    "nearestStation": "白金高輪駅 徒歩5分 / 三田駅 徒歩10分",
    "website": "https://www.city.minato.tokyo.jp/kodomo/kodomo/kodomo/hoikuen/14/index.html",
    "lat": 35.643,
    "lng": 139.738,
    "operator": "港区",
    "notes": "高輪地区の区立認可保育園。定員149名。"
  },
  {
    "slug": "takanawa-38",
    "name": "高輪保育園",
    "type": "licensed",
    "area": "takanawa-shirokane",
    "address": "港区高輪3-18-15",
    "phone": "03-3449-1641",
    "hours": {
      "standard": "7:15-18:15",
      "extended": "18:15-20:15",
      "shortTime": null
    },
    "ageMin": 0,
    "ageMax": 5,
    "capacity": 143,
    "features": [
      "園庭あり",
      "延長保育",
      "障害児保育"
    ],
    "hasGarden": true,
    "nearestStation": "品川駅 徒歩8分 / 高輪ゲートウェイ駅 徒歩6分",
    "website": "https://www.city.minato.tokyo.jp/kodomo/kodomo/kodomo/hoikuen/16/index.html",
    "lat": 35.6328,
    "lng": 139.7362,
    "operator": "港区",
    "notes": "高輪地区の区立認可保育園。定員143名。"
  },
  {
    "slug": "takanawa-39",
    "name": "白金保育園",
    "type": "licensed",
    "area": "takanawa-shirokane",
    "address": "港区白金3-10-12",
    "phone": "03-3441-5076",
    "hours": {
      "standard": "7:15-18:15",
      "extended": "18:15-20:15",
      "shortTime": null
    },
    "ageMin": 0,
    "ageMax": 5,
    "capacity": 100,
    "features": [
      "園庭あり",
      "延長保育",
      "障害児保育"
    ],
    "hasGarden": true,
    "nearestStation": "白金高輪駅 徒歩8分",
    "website": "https://www.city.minato.tokyo.jp/kodomo/kodomo/kodomo/hoikuen/15/index.html",
    "lat": 35.641,
    "lng": 139.7268,
    "operator": "港区",
    "notes": "高輪地区の区立認可保育園。定員100名。"
  },
  {
    "slug": "takanawa-40",
    "name": "神応保育園",
    "type": "licensed",
    "area": "takanawa-shirokane",
    "address": "港区白金6-9-5",
    "phone": "03-5422-6363",
    "hours": {
      "standard": "7:15-18:15",
      "extended": "18:15-22:00",
      "shortTime": null
    },
    "ageMin": 0,
    "ageMax": 5,
    "capacity": 114,
    "features": [
      "園庭あり",
      "延長保育",
      "障害児保育"
    ],
    "hasGarden": true,
    "nearestStation": "白金台駅 徒歩5分",
    "website": "https://www.city.minato.tokyo.jp/uneishien/hoikuen/shinnou.html",
    "lat": 35.638,
    "lng": 139.725,
    "operator": "港区",
    "notes": "高輪地区の区立認可保育園。定員114名。"
  },
  {
    "slug": "takanawa-41",
    "name": "ゆらりん高輪保育園",
    "type": "licensed",
    "area": "takanawa-shirokane",
    "address": "港区高輪1-5-38",
    "phone": "03-5422-6170",
    "hours": {
      "standard": "7:15-18:15",
      "extended": "18:15-20:15",
      "shortTime": null
    },
    "ageMin": 0,
    "ageMax": 5,
    "capacity": 101,
    "features": [
      "延長保育",
      "食育"
    ],
    "hasGarden": false,
    "nearestStation": "白金高輪駅 徒歩3分",
    "website": "https://hoiku.merhalsa.jp/yurarin-takanawa/",
    "lat": 35.6385,
    "lng": 139.7345,
    "operator": "ライフサポート株式会社",
    "notes": "高輪地区の私立認可保育園。定員101名。"
  },
  {
    "slug": "takanawa-42",
    "name": "愛星保育園",
    "type": "licensed",
    "area": "takanawa-shirokane",
    "address": "港区高輪1-27-40",
    "phone": "03-3441-5410",
    "hours": {
      "standard": "7:15-18:15",
      "extended": "18:15-20:15",
      "shortTime": null
    },
    "ageMin": 0,
    "ageMax": 5,
    "capacity": 65,
    "features": [
      "延長保育",
      "食育"
    ],
    "hasGarden": false,
    "nearestStation": "高輪台駅 徒歩5分",
    "website": "https://www.aiseihoikuen.or.jp/",
    "lat": 35.636,
    "lng": 139.734,
    "operator": "社会福祉法人愛星学園",
    "notes": "高輪地区の私立認可保育園。定員65名。"
  },
  {
    "slug": "takanawa-43",
    "name": "さくらさくみらい高輪",
    "type": "licensed",
    "area": "takanawa-shirokane",
    "address": "港区高輪2-6-21",
    "phone": "03-5860-2339",
    "hours": {
      "standard": "7:15-18:15",
      "extended": "18:15-20:15",
      "shortTime": null
    },
    "ageMin": 0,
    "ageMax": 5,
    "capacity": 84,
    "features": [
      "延長保育",
      "食育"
    ],
    "hasGarden": false,
    "nearestStation": "高輪台駅 徒歩3分 / 白金高輪駅 徒歩8分",
    "website": "https://www.sakura-39.jp/hoiku/takanawa",
    "lat": 35.6365,
    "lng": 139.7325,
    "operator": "株式会社さくらさくみらい",
    "notes": "高輪地区の私立認可保育園。定員84名。"
  },
  {
    "slug": "takanawa-44",
    "name": "ニチイキッズ白金台保育園",
    "type": "licensed",
    "area": "takanawa-shirokane",
    "address": "港区白金台2-26-10",
    "phone": "03-5791-2161",
    "hours": {
      "standard": "7:15-18:15",
      "extended": "18:15-20:15",
      "shortTime": null
    },
    "ageMin": 0,
    "ageMax": 5,
    "capacity": 70,
    "features": [
      "延長保育",
      "食育"
    ],
    "hasGarden": false,
    "nearestStation": "白金台駅 徒歩5分 / 高輪台駅 徒歩5分",
    "website": "https://www.nichiikids.net/nursery/other/shiroganedai/index.html",
    "lat": 35.6395,
    "lng": 139.724,
    "operator": "株式会社ニチイ学館",
    "notes": "高輪地区の私立認可保育園。定員70名。"
  },
  {
    "slug": "takanawa-45",
    "name": "アイグラン保育園白金台",
    "type": "licensed",
    "area": "takanawa-shirokane",
    "address": "港区白金台3-13-18",
    "phone": "03-6277-4494",
    "hours": {
      "standard": "7:15-18:15",
      "extended": "18:15-20:15",
      "shortTime": null
    },
    "ageMin": 0,
    "ageMax": 5,
    "capacity": 58,
    "features": [
      "延長保育",
      "食育"
    ],
    "hasGarden": false,
    "nearestStation": "白金台駅 徒歩3分",
    "website": "https://aigran.co.jp/nursery/ninka/nursery-3611/",
    "lat": 35.6391,
    "lng": 139.7244,
    "operator": "株式会社アイグラン",
    "notes": "高輪地区の私立認可保育園。定員58名。"
  },
  {
    "slug": "takanawa-46",
    "name": "うれしい保育園白金高輪",
    "type": "licensed",
    "area": "takanawa-shirokane",
    "address": "港区三田5-17-2",
    "phone": "03-5795-2310",
    "hours": {
      "standard": "7:15-18:15",
      "extended": "18:15-20:15",
      "shortTime": null
    },
    "ageMin": 0,
    "ageMax": 5,
    "capacity": 60,
    "features": [
      "延長保育",
      "食育"
    ],
    "hasGarden": false,
    "nearestStation": "白金高輪駅 徒歩5分",
    "website": "https://www.ureshii-h.jp/place/shirokanetakanawa/",
    "lat": 35.642,
    "lng": 139.738,
    "operator": "株式会社グローバルキッズCOMPANY",
    "notes": "高輪地区の私立認可保育園。定員60名。"
  },
  {
    "slug": "shibaura-47",
    "name": "しばうら保育園",
    "type": "licensed",
    "area": "daiba-shibaura",
    "address": "港区芝浦3-1-16",
    "phone": "03-5232-1130",
    "hours": {
      "standard": "7:15-18:15",
      "extended": "18:15-22:00",
      "shortTime": null
    },
    "ageMin": 0,
    "ageMax": 5,
    "capacity": 216,
    "features": [
      "園庭あり",
      "延長保育",
      "障害児保育"
    ],
    "hasGarden": true,
    "nearestStation": "田町駅 徒歩5分",
    "website": "https://www.city.minato.tokyo.jp/kodomo/kodomo/kodomo/hoikuen/23/index.html",
    "lat": 35.6445,
    "lng": 139.75,
    "operator": "港区",
    "notes": "芝浦港南地区の区立認可保育園。定員216名。"
  },
  {
    "slug": "shibaura-48",
    "name": "しばうら保育園分園",
    "type": "licensed",
    "area": "daiba-shibaura",
    "address": "港区芝浦1-16-1",
    "phone": "03-6453-6346",
    "hours": {
      "standard": "7:15-18:15",
      "extended": "18:15-22:00",
      "shortTime": null
    },
    "ageMin": 0,
    "ageMax": 5,
    "capacity": 36,
    "features": [
      "園庭あり",
      "延長保育",
      "障害児保育"
    ],
    "hasGarden": false,
    "nearestStation": "田町駅 徒歩7分",
    "website": "https://www.city.minato.tokyo.jp/kodomo/kodomo/kodomo/hoikuen/23/index.html",
    "lat": 35.646,
    "lng": 139.7488,
    "operator": "港区",
    "notes": "芝浦港南地区の区立認可保育園。定員36名。"
  },
  {
    "slug": "shibaura-49",
    "name": "こうなん保育園",
    "type": "licensed",
    "area": "daiba-shibaura",
    "address": "港区港南4-2-3-101",
    "phone": "03-3450-3800",
    "hours": {
      "standard": "7:15-18:15",
      "extended": "18:15-20:15",
      "shortTime": null
    },
    "ageMin": 0,
    "ageMax": 5,
    "capacity": 148,
    "features": [
      "園庭あり",
      "延長保育",
      "障害児保育"
    ],
    "hasGarden": true,
    "nearestStation": "品川駅 徒歩12分",
    "website": "https://www.city.minato.tokyo.jp/kodomo/kodomo/kodomo/hoikuen/08/index.html",
    "lat": 35.6265,
    "lng": 139.745,
    "operator": "港区",
    "notes": "芝浦港南地区の区立認可保育園。定員148名。"
  },
  {
    "slug": "shibaura-50",
    "name": "たかはま保育園",
    "type": "licensed",
    "area": "daiba-shibaura",
    "address": "港区港南4-3-7",
    "phone": "03-5781-0255",
    "hours": {
      "standard": "7:15-18:15",
      "extended": "18:15-22:00",
      "shortTime": null
    },
    "ageMin": 0,
    "ageMax": 5,
    "capacity": 151,
    "features": [
      "園庭あり",
      "延長保育",
      "障害児保育"
    ],
    "hasGarden": true,
    "nearestStation": "品川駅 徒歩12分",
    "website": "https://www.city.minato.tokyo.jp/kodomo/kodomo/kodomo/hoikuen/22/index.html",
    "lat": 35.626,
    "lng": 139.7445,
    "operator": "港区",
    "notes": "芝浦港南地区の区立認可保育園。定員151名。"
  },
  {
    "slug": "shibaura-51",
    "name": "台場保育園",
    "type": "licensed",
    "area": "daiba-shibaura",
    "address": "港区台場1-5-1",
    "phone": "03-5500-2360",
    "hours": {
      "standard": "7:15-18:15",
      "extended": "18:15-20:15",
      "shortTime": null
    },
    "ageMin": 0,
    "ageMax": 5,
    "capacity": 131,
    "features": [
      "園庭あり",
      "延長保育",
      "障害児保育"
    ],
    "hasGarden": true,
    "nearestStation": "お台場海浜公園駅 徒歩3分",
    "website": "https://www.city.minato.tokyo.jp/kodomo/kodomo/kodomo/hoikuen/04/index.html",
    "lat": 35.629,
    "lng": 139.775,
    "operator": "港区",
    "notes": "芝浦港南地区の区立認可保育園。定員131名。"
  },
  {
    "slug": "shibaura-52",
    "name": "太陽の子シーバンス保育園",
    "type": "licensed",
    "area": "daiba-shibaura",
    "address": "港区芝浦1-2-2",
    "phone": "03-5439-4014",
    "hours": {
      "standard": "7:15-18:15",
      "extended": "18:15-20:15",
      "shortTime": null
    },
    "ageMin": 0,
    "ageMax": 5,
    "capacity": 100,
    "features": [
      "延長保育",
      "食育"
    ],
    "hasGarden": false,
    "nearestStation": "浜松町駅 徒歩8分 / 田町駅 徒歩8分",
    "website": "https://www.kidslife-nursery.com/facility/tokyo/minato/seavans/",
    "lat": 35.6475,
    "lng": 139.751,
    "operator": "HITOWAキッズライフ株式会社",
    "notes": "芝浦港南地区の私立認可保育園。定員100名。"
  },
  {
    "slug": "shibaura-53",
    "name": "アンジェリカ田町保育園",
    "type": "licensed",
    "area": "daiba-shibaura",
    "address": "港区芝浦1-6-41",
    "phone": "03-6435-2157",
    "hours": {
      "standard": "7:15-18:15",
      "extended": "18:15-20:30",
      "shortTime": null
    },
    "ageMin": 0,
    "ageMax": 5,
    "capacity": 60,
    "features": [
      "延長保育",
      "食育"
    ],
    "hasGarden": false,
    "nearestStation": "田町駅 徒歩3分",
    "website": "https://www.angelica-nsy.net/facilities/tamachihoiku/",
    "lat": 35.6465,
    "lng": 139.7495,
    "operator": "株式会社アンジェリカ",
    "notes": "芝浦港南地区の私立認可保育園。定員60名。"
  },
  {
    "slug": "shibaura-54",
    "name": "にじのいるか保育園芝浦",
    "type": "licensed",
    "area": "daiba-shibaura",
    "address": "港区芝浦2-3-31",
    "phone": "03-6435-3804",
    "hours": {
      "standard": "7:15-18:15",
      "extended": "18:15-20:15",
      "shortTime": null
    },
    "ageMin": 0,
    "ageMax": 5,
    "capacity": 60,
    "features": [
      "延長保育",
      "食育"
    ],
    "hasGarden": false,
    "nearestStation": "田町駅 徒歩8分",
    "website": "https://www.nijinoiruka.ed.jp/nursery/shibaura/",
    "lat": 35.6452,
    "lng": 139.7505,
    "operator": "学校法人滋慶学園",
    "notes": "芝浦港南地区の私立認可保育園。定員60名。"
  },
  {
    "slug": "shibaura-55",
    "name": "アスク芝浦4丁目保育園",
    "type": "licensed",
    "area": "daiba-shibaura",
    "address": "港区芝浦4-12-28",
    "phone": "03-6435-2855",
    "hours": {
      "standard": "7:15-18:15",
      "extended": "18:15-20:15",
      "shortTime": null
    },
    "ageMin": 0,
    "ageMax": 5,
    "capacity": 51,
    "features": [
      "延長保育",
      "食育"
    ],
    "hasGarden": false,
    "nearestStation": "田町駅 徒歩12分",
    "website": "https://list.nihonhoiku.co.jp/nursery/detail/shibaura4/",
    "lat": 35.6399,
    "lng": 139.753,
    "operator": "株式会社日本保育サービス",
    "notes": "芝浦港南地区の私立認可保育園。定員51名。"
  },
  {
    "slug": "shibaura-56",
    "name": "グローバルキッズ港南保育園",
    "type": "licensed",
    "area": "daiba-shibaura",
    "address": "港区港南4-1-8",
    "phone": "03-3450-6130",
    "hours": {
      "standard": "7:15-18:15",
      "extended": "18:15-20:15",
      "shortTime": null
    },
    "ageMin": 0,
    "ageMax": 5,
    "capacity": 99,
    "features": [
      "延長保育",
      "食育"
    ],
    "hasGarden": false,
    "nearestStation": "品川駅 徒歩10分",
    "website": "https://www.gkids.co.jp/facilities/nursery_072.html",
    "lat": 35.627,
    "lng": 139.7455,
    "operator": "株式会社グローバルキッズ",
    "notes": "芝浦港南地区の私立認可保育園。定員99名。"
  },
  {
    "slug": "shibaura-57",
    "name": "ベネッセ港南保育園",
    "type": "licensed",
    "area": "daiba-shibaura",
    "address": "港区港南4-6-7",
    "phone": "03-5783-5871",
    "hours": {
      "standard": "7:15-18:15",
      "extended": "18:15-22:00",
      "shortTime": null
    },
    "ageMin": 0,
    "ageMax": 5,
    "capacity": 60,
    "features": [
      "延長保育",
      "食育"
    ],
    "hasGarden": false,
    "nearestStation": "品川駅 徒歩15分",
    "website": "https://hoiku.benesse-style-care.co.jp/facilities/area_tokyo/minato/h-kounan/",
    "lat": 35.6255,
    "lng": 139.744,
    "operator": "株式会社ベネッセスタイルケア",
    "notes": "芝浦港南地区の私立認可保育園。定員60名。"
  },
  {
    "slug": "shibaura-58",
    "name": "ゆらりん港南緑水保育園",
    "type": "licensed",
    "area": "daiba-shibaura",
    "address": "港区港南4-7-37",
    "phone": "03-5781-2781",
    "hours": {
      "standard": "7:15-18:15",
      "extended": "18:15-20:15",
      "shortTime": null
    },
    "ageMin": 0,
    "ageMax": 5,
    "capacity": 101,
    "features": [
      "延長保育",
      "食育"
    ],
    "hasGarden": true,
    "nearestStation": "品川駅 徒歩15分",
    "website": "https://hoiku.merhalsa.jp/yurarin-ryokusui/",
    "lat": 35.625,
    "lng": 139.7435,
    "operator": "ライフサポート株式会社",
    "notes": "芝浦港南地区の私立認可保育園。定員101名。"
  },
  {
    "slug": "shibaura-59",
    "name": "にじいろ保育園海岸三丁目",
    "type": "licensed",
    "area": "daiba-shibaura",
    "address": "港区海岸3-16-6",
    "phone": "03-6722-6865",
    "hours": {
      "standard": "7:15-18:15",
      "extended": "18:15-20:15",
      "shortTime": null
    },
    "ageMin": 0,
    "ageMax": 5,
    "capacity": 125,
    "features": [
      "延長保育",
      "食育"
    ],
    "hasGarden": false,
    "nearestStation": "田町駅 徒歩15分",
    "website": "https://www.like-kd.co.jp/establishment/nijiiro/HPkaigansanchome",
    "lat": 35.636,
    "lng": 139.755,
    "operator": "ライクキッズ株式会社",
    "notes": "芝浦港南地区の私立認可保育園。定員125名。"
  },
  {
    "slug": "shibaura-island-kodomoen",
    "name": "芝浦アイランドこども園",
    "type": "kodomoen",
    "area": "daiba-shibaura",
    "address": "港区芝浦4-20-1",
    "phone": "03-5443-7337",
    "hours": {
      "standard": "7:15-18:15",
      "extended": "18:15-22:00",
      "shortTime": "9:00-14:00"
    },
    "ageMin": 0,
    "ageMax": 5,
    "capacity": 171,
    "features": [
      "園庭あり",
      "延長保育",
      "教育・保育一体",
      "障害児保育"
    ],
    "hasGarden": true,
    "nearestStation": "田町駅 徒歩15分",
    "website": "https://www.tokyoymca.org/childcare/shibaura-kodomo/",
    "lat": 35.638,
    "lng": 139.754,
    "operator": "港区",
    "notes": "芝浦アイランド内の区立認定こども園。定員171名。教育と保育を一体的に提供。短時間利用（幼稚園型）も可能。"
  },
  {
    "slug": "small-61",
    "name": "こころナーサリー新橋",
    "type": "small-scale",
    "area": "shiba-mita",
    "address": "港区新橋5-35-10",
    "phone": "03-6435-8377",
    "hours": {
      "standard": "7:30-18:30",
      "extended": "18:30-20:15",
      "shortTime": null
    },
    "ageMin": 0,
    "ageMax": 2,
    "capacity": 18,
    "features": [
      "少人数制",
      "家庭的保育",
      "延長保育"
    ],
    "hasGarden": false,
    "nearestStation": "新橋駅 徒歩5分 / 御成門駅 徒歩5分",
    "website": "https://www.taiyo.ed.jp/nursery/shinbashi/",
    "lat": 35.658,
    "lng": 139.752,
    "operator": "私立",
    "notes": "定員18名の小規模保育事業。0〜2歳児対象。少人数ならではのきめ細やかな保育。"
  },
  {
    "slug": "small-62",
    "name": "ふらわぁきっず保育園新橋",
    "type": "small-scale",
    "area": "shiba-mita",
    "address": "港区新橋3-3-13",
    "phone": "03-6550-8800",
    "hours": {
      "standard": "7:30-18:30",
      "extended": "18:30-20:15",
      "shortTime": null
    },
    "ageMin": 0,
    "ageMax": 2,
    "capacity": 12,
    "features": [
      "少人数制",
      "家庭的保育",
      "延長保育"
    ],
    "hasGarden": false,
    "nearestStation": "新橋駅 徒歩3分",
    "website": "http://flower-kids.com/",
    "lat": 35.661,
    "lng": 139.7545,
    "operator": "私立",
    "notes": "定員12名の小規模保育事業。0〜2歳児対象。少人数ならではのきめ細やかな保育。"
  },
  {
    "slug": "small-63",
    "name": "デイジー保育園麻布十番",
    "type": "small-scale",
    "area": "azabu",
    "address": "港区麻布十番3-10-12",
    "phone": "03-6809-6353",
    "hours": {
      "standard": "7:30-18:30",
      "extended": "18:30-20:15",
      "shortTime": null
    },
    "ageMin": 0,
    "ageMax": 2,
    "capacity": 18,
    "features": [
      "少人数制",
      "家庭的保育",
      "延長保育"
    ],
    "hasGarden": false,
    "nearestStation": "麻布十番駅 徒歩3分",
    "website": "https://threepeace.life/service/daisy-nursery/daisyazabujuban/",
    "lat": 35.652,
    "lng": 139.7355,
    "operator": "私立",
    "notes": "定員18名の小規模保育事業。0〜2歳児対象。少人数ならではのきめ細やかな保育。"
  },
  {
    "slug": "small-64",
    "name": "デイジー保育園麻布十番フォレスト",
    "type": "small-scale",
    "area": "azabu",
    "address": "港区麻布十番3-10-12",
    "phone": "03-5439-9241",
    "hours": {
      "standard": "7:30-18:30",
      "extended": "18:30-20:15",
      "shortTime": null
    },
    "ageMin": 0,
    "ageMax": 2,
    "capacity": 18,
    "features": [
      "少人数制",
      "家庭的保育",
      "延長保育"
    ],
    "hasGarden": false,
    "nearestStation": "麻布十番駅 徒歩3分",
    "website": "https://threepeace.life/service/daisy-nursery/daisyazabujubanforest/",
    "lat": 35.652,
    "lng": 139.7355,
    "operator": "私立",
    "notes": "定員18名の小規模保育事業。0〜2歳児対象。少人数ならではのきめ細やかな保育。"
  },
  {
    "slug": "small-65",
    "name": "ここいく保育園西麻布",
    "type": "small-scale",
    "area": "azabu",
    "address": "港区西麻布4-10-1",
    "phone": "03-6419-7333",
    "hours": {
      "standard": "7:30-18:30",
      "extended": "18:30-20:15",
      "shortTime": null
    },
    "ageMin": 0,
    "ageMax": 2,
    "capacity": 19,
    "features": [
      "少人数制",
      "家庭的保育",
      "延長保育"
    ],
    "hasGarden": false,
    "nearestStation": "広尾駅 徒歩8分 / 六本木駅 徒歩10分",
    "website": "https://cocoiku-hoikuen.com/",
    "lat": 35.657,
    "lng": 139.721,
    "operator": "私立",
    "notes": "定員19名の小規模保育事業。0〜2歳児対象。少人数ならではのきめ細やかな保育。"
  },
  {
    "slug": "small-66",
    "name": "sakura保育園赤坂",
    "type": "small-scale",
    "area": "akasaka-aoyama",
    "address": "港区赤坂2-12-17",
    "phone": "03-6426-5097",
    "hours": {
      "standard": "7:30-18:30",
      "extended": "18:30-19:30",
      "shortTime": null
    },
    "ageMin": 0,
    "ageMax": 2,
    "capacity": 13,
    "features": [
      "少人数制",
      "家庭的保育",
      "延長保育"
    ],
    "hasGarden": false,
    "nearestStation": "溜池山王駅 徒歩3分 / 赤坂駅 徒歩5分",
    "website": "https://sakurakids.net/",
    "lat": 35.6735,
    "lng": 139.738,
    "operator": "私立",
    "notes": "定員13名の小規模保育事業。0〜2歳児対象。少人数ならではのきめ細やかな保育。"
  },
  {
    "slug": "small-67",
    "name": "ふらわぁきっず保育園三田",
    "type": "small-scale",
    "area": "takanawa-shirokane",
    "address": "港区三田5-5-7",
    "phone": "03-6809-5303",
    "hours": {
      "standard": "7:30-18:30",
      "extended": "18:30-20:15",
      "shortTime": null
    },
    "ageMin": 0,
    "ageMax": 2,
    "capacity": 12,
    "features": [
      "少人数制",
      "家庭的保育",
      "延長保育"
    ],
    "hasGarden": false,
    "nearestStation": "白金高輪駅 徒歩5分",
    "website": "http://flower-kids.com/",
    "lat": 35.6425,
    "lng": 139.7385,
    "operator": "私立",
    "notes": "定員12名の小規模保育事業。0〜2歳児対象。少人数ならではのきめ細やかな保育。"
  },
  {
    "slug": "small-68",
    "name": "ちゃいるど・はっぴっぴ!!白金保育園",
    "type": "small-scale",
    "area": "takanawa-shirokane",
    "address": "港区白金3-2-9",
    "phone": "03-6629-5180",
    "hours": {
      "standard": "7:30-18:30",
      "extended": "18:30-19:30",
      "shortTime": null
    },
    "ageMin": 0,
    "ageMax": 2,
    "capacity": 10,
    "features": [
      "少人数制",
      "家庭的保育",
      "延長保育"
    ],
    "hasGarden": false,
    "nearestStation": "白金高輪駅 徒歩5分",
    "website": "https://happy-pi.com/",
    "lat": 35.6418,
    "lng": 139.7275,
    "operator": "私立",
    "notes": "定員10名の小規模保育事業。0〜2歳児対象。少人数ならではのきめ細やかな保育。"
  },
  {
    "slug": "small-69",
    "name": "港南あおぞら保育園",
    "type": "small-scale",
    "area": "daiba-shibaura",
    "address": "港区港南3-8-1",
    "phone": "03-6712-1988",
    "hours": {
      "standard": "7:30-18:30",
      "extended": "18:30-19:15",
      "shortTime": null
    },
    "ageMin": 0,
    "ageMax": 2,
    "capacity": 19,
    "features": [
      "少人数制",
      "家庭的保育",
      "延長保育"
    ],
    "hasGarden": false,
    "nearestStation": "品川駅 徒歩10分",
    "website": "http://kounan-aozora.jp/",
    "lat": 35.628,
    "lng": 139.746,
    "operator": "私立",
    "notes": "定員19名の小規模保育事業。0〜2歳児対象。少人数ならではのきめ細やかな保育。"
  },
  {
    "slug": "small-70",
    "name": "にじのそら保育園芝浦",
    "type": "small-scale",
    "area": "daiba-shibaura",
    "address": "港区芝浦1-14-6",
    "phone": "03-6722-0425",
    "hours": {
      "standard": "7:30-18:30",
      "extended": "18:30-20:15",
      "shortTime": null
    },
    "ageMin": 0,
    "ageMax": 2,
    "capacity": 19,
    "features": [
      "少人数制",
      "家庭的保育",
      "延長保育"
    ],
    "hasGarden": false,
    "nearestStation": "田町駅 徒歩8分",
    "website": "https://nijinosora.info/",
    "lat": 35.6462,
    "lng": 139.7492,
    "operator": "私立",
    "notes": "定員19名の小規模保育事業。0〜2歳児対象。少人数ならではのきめ細やかな保育。"
  },
  {
    "slug": "room-71",
    "name": "芝公園二丁目保育室",
    "type": "minato-room",
    "area": "shiba-mita",
    "address": "港区芝公園2-12-10",
    "phone": "03-3436-6611",
    "hours": {
      "standard": "7:30-18:30",
      "extended": "18:30-20:15",
      "shortTime": null
    },
    "ageMin": 0,
    "ageMax": 5,
    "capacity": 72,
    "features": [
      "港区独自事業",
      "延長保育",
      "認可園転園加点"
    ],
    "hasGarden": false,
    "nearestStation": "芝公園駅 徒歩3分",
    "website": "https://www.city.minato.tokyo.jp/shisetsu/gakkokyoiku/hoikuen/109.html",
    "lat": 35.6548,
    "lng": 139.746,
    "operator": "港区（委託）",
    "notes": "港区独自の保育施設。定員72名。認可保育園に入れなかった場合の受け皿。認可園申込時に加点あり。"
  },
  {
    "slug": "room-72",
    "name": "南麻布三丁目保育室",
    "type": "minato-room",
    "area": "azabu",
    "address": "港区南麻布3-5-15",
    "phone": "03-3443-5711",
    "hours": {
      "standard": "7:30-18:30",
      "extended": "18:30-20:15",
      "shortTime": null
    },
    "ageMin": 0,
    "ageMax": 5,
    "capacity": 15,
    "features": [
      "港区独自事業",
      "延長保育",
      "認可園転園加点"
    ],
    "hasGarden": false,
    "nearestStation": "白金高輪駅 徒歩8分 / 麻布十番駅 徒歩10分",
    "website": "https://www.city.minato.tokyo.jp/shisetsu/gakkokyoiku/hoikuen/110.html",
    "lat": 35.649,
    "lng": 139.728,
    "operator": "港区（委託）",
    "notes": "港区独自の保育施設。定員15名。認可保育園に入れなかった場合の受け皿。認可園申込時に加点あり。"
  },
  {
    "slug": "room-73",
    "name": "青南保育室",
    "type": "minato-room",
    "area": "akasaka-aoyama",
    "address": "港区南青山4-19-18",
    "phone": "03-5770-3933",
    "hours": {
      "standard": "7:30-18:30",
      "extended": "18:30-20:15",
      "shortTime": null
    },
    "ageMin": 0,
    "ageMax": 5,
    "capacity": 96,
    "features": [
      "港区独自事業",
      "延長保育",
      "認可園転園加点"
    ],
    "hasGarden": false,
    "nearestStation": "表参道駅 徒歩5分",
    "website": "https://www.city.minato.tokyo.jp/shisetsu/gakkokyoiku/hoikuen/56.html",
    "lat": 35.664,
    "lng": 139.7145,
    "operator": "港区（委託）",
    "notes": "港区独自の保育施設。定員96名。認可保育園に入れなかった場合の受け皿。認可園申込時に加点あり。"
  },
  {
    "slug": "room-74",
    "name": "第二青南保育室",
    "type": "minato-room",
    "area": "akasaka-aoyama",
    "address": "港区南青山4-19-5",
    "phone": "03-5770-5366",
    "hours": {
      "standard": "7:30-18:30",
      "extended": "18:30-20:15",
      "shortTime": null
    },
    "ageMin": 0,
    "ageMax": 5,
    "capacity": 75,
    "features": [
      "港区独自事業",
      "延長保育",
      "認可園転園加点"
    ],
    "hasGarden": false,
    "nearestStation": "表参道駅 徒歩5分",
    "website": "https://www.city.minato.tokyo.jp/shisetsu/gakkokyoiku/hoikuen/111.html",
    "lat": 35.6642,
    "lng": 139.7148,
    "operator": "港区（委託）",
    "notes": "港区独自の保育施設。定員75名。認可保育園に入れなかった場合の受け皿。認可園申込時に加点あり。"
  },
  {
    "slug": "room-75",
    "name": "桂坂保育室",
    "type": "minato-room",
    "area": "takanawa-shirokane",
    "address": "港区高輪3-19-36",
    "phone": "03-5475-6646",
    "hours": {
      "standard": "7:30-18:30",
      "extended": "18:30-20:15",
      "shortTime": null
    },
    "ageMin": 0,
    "ageMax": 5,
    "capacity": 138,
    "features": [
      "港区独自事業",
      "延長保育",
      "認可園転園加点"
    ],
    "hasGarden": false,
    "nearestStation": "品川駅 徒歩8分 / 高輪ゲートウェイ駅 徒歩5分",
    "website": "https://www.city.minato.tokyo.jp/shisetsu/gakkokyoiku/hoikuen/57.html",
    "lat": 35.6322,
    "lng": 139.7358,
    "operator": "港区（委託）",
    "notes": "港区独自の保育施設。定員138名。認可保育園に入れなかった場合の受け皿。認可園申込時に加点あり。"
  },
  {
    "slug": "room-76",
    "name": "志田町保育室",
    "type": "minato-room",
    "area": "takanawa-shirokane",
    "address": "港区白金1-11-16",
    "phone": "03-6277-2582",
    "hours": {
      "standard": "7:30-18:30",
      "extended": "18:30-20:15",
      "shortTime": null
    },
    "ageMin": 0,
    "ageMax": 5,
    "capacity": 119,
    "features": [
      "港区独自事業",
      "延長保育",
      "認可園転園加点"
    ],
    "hasGarden": false,
    "nearestStation": "白金高輪駅 徒歩3分",
    "website": "https://www.city.minato.tokyo.jp/shisetsu/gakkokyoiku/hoikuen/112.html",
    "lat": 35.642,
    "lng": 139.731,
    "operator": "港区（委託）",
    "notes": "港区独自の保育施設。定員119名。認可保育園に入れなかった場合の受け皿。認可園申込時に加点あり。"
  },
  {
    "slug": "room-77",
    "name": "白金三丁目保育室",
    "type": "minato-room",
    "area": "takanawa-shirokane",
    "address": "港区白金3-7-13",
    "phone": "03-6455-7171",
    "hours": {
      "standard": "7:30-18:30",
      "extended": "18:30-20:15",
      "shortTime": null
    },
    "ageMin": 0,
    "ageMax": 5,
    "capacity": 44,
    "features": [
      "港区独自事業",
      "延長保育",
      "認可園転園加点"
    ],
    "hasGarden": false,
    "nearestStation": "白金高輪駅 徒歩6分",
    "website": "https://www.city.minato.tokyo.jp/shisetsu/gakkokyoiku/hoikuen/58.html",
    "lat": 35.6415,
    "lng": 139.7265,
    "operator": "港区（委託）",
    "notes": "港区独自の保育施設。定員44名。認可保育園に入れなかった場合の受け皿。認可園申込時に加点あり。"
  },
  {
    "slug": "room-78",
    "name": "たまち保育室",
    "type": "minato-room",
    "area": "daiba-shibaura",
    "address": "港区芝浦3-4-1",
    "phone": "03-5484-6088",
    "hours": {
      "standard": "7:30-18:30",
      "extended": "18:30-20:15",
      "shortTime": null
    },
    "ageMin": 0,
    "ageMax": 5,
    "capacity": 141,
    "features": [
      "港区独自事業",
      "延長保育",
      "認可園転園加点"
    ],
    "hasGarden": false,
    "nearestStation": "田町駅 徒歩3分",
    "website": "https://www.city.minato.tokyo.jp/shisetsu/gakkokyoiku/hoikuen/113.html",
    "lat": 35.6446,
    "lng": 139.7498,
    "operator": "港区（委託）",
    "notes": "港区独自の保育施設。定員141名。認可保育園に入れなかった場合の受け皿。認可園申込時に加点あり。"
  },
  {
    "slug": "room-79",
    "name": "芝浦橋保育室",
    "type": "minato-room",
    "area": "daiba-shibaura",
    "address": "港区芝浦4-6-8",
    "phone": "03-6865-1004",
    "hours": {
      "standard": "7:30-18:30",
      "extended": "18:30-20:15",
      "shortTime": null
    },
    "ageMin": 0,
    "ageMax": 5,
    "capacity": 175,
    "features": [
      "港区独自事業",
      "延長保育",
      "認可園転園加点"
    ],
    "hasGarden": false,
    "nearestStation": "田町駅 徒歩10分",
    "website": "https://www.city.minato.tokyo.jp/shisetsu/gakkokyoiku/hoikuen/59.html",
    "lat": 35.641,
    "lng": 139.7525,
    "operator": "港区（委託）",
    "notes": "港区独自の保育施設。定員175名。認可保育園に入れなかった場合の受け皿。認可園申込時に加点あり。"
  },
  {
    "slug": "room-80",
    "name": "五色橋保育室",
    "type": "minato-room",
    "area": "daiba-shibaura",
    "address": "港区海岸3-5-13",
    "phone": "03-6435-3201",
    "hours": {
      "standard": "7:30-18:30",
      "extended": "18:30-20:15",
      "shortTime": null
    },
    "ageMin": 0,
    "ageMax": 5,
    "capacity": 65,
    "features": [
      "港区独自事業",
      "延長保育",
      "認可園転園加点"
    ],
    "hasGarden": false,
    "nearestStation": "田町駅 徒歩12分",
    "website": "https://www.city.minato.tokyo.jp/shisetsu/gakkokyoiku/hoikuen/114.html",
    "lat": 35.637,
    "lng": 139.7555,
    "operator": "港区（委託）",
    "notes": "港区独自の保育施設。定員65名。認可保育園に入れなかった場合の受け皿。認可園申込時に加点あり。"
  },
  {
    "slug": "cert-81",
    "name": "三田プチ・クレイシュ",
    "type": "certified",
    "area": "shiba-mita",
    "address": "港区芝5-29-22",
    "phone": "03-5440-5950",
    "hours": {
      "standard": "7:00-20:00",
      "extended": null,
      "shortTime": null
    },
    "ageMin": 0,
    "ageMax": 5,
    "capacity": 33,
    "features": [
      "認証保育所",
      "延長保育",
      "少人数制"
    ],
    "hasGarden": false,
    "nearestStation": "田町駅 徒歩3分 / 三田駅 徒歩5分",
    "website": "http://kodomonomori.co.jp/mi/",
    "lat": 35.6505,
    "lng": 139.746,
    "operator": "私立",
    "notes": "東京都認証保育所。定員33名。営業時間7:00-20:00。"
  },
  {
    "slug": "cert-82",
    "name": "プチ・ナーサリー田町",
    "type": "certified",
    "area": "shiba-mita",
    "address": "港区芝4-16-1",
    "phone": "03-3451-5670",
    "hours": {
      "standard": "7:00-20:00",
      "extended": null,
      "shortTime": null
    },
    "ageMin": 0,
    "ageMax": 5,
    "capacity": 40,
    "features": [
      "認証保育所",
      "延長保育",
      "少人数制"
    ],
    "hasGarden": false,
    "nearestStation": "田町駅 徒歩5分",
    "website": "http://kodomonomori.co.jp/tm/",
    "lat": 35.651,
    "lng": 139.7455,
    "operator": "私立",
    "notes": "東京都認証保育所。定員40名。営業時間7:00-20:00。"
  },
  {
    "slug": "cert-83",
    "name": "ホームデイケア・六本木",
    "type": "certified",
    "area": "azabu",
    "address": "港区西麻布1-4-46",
    "phone": "03-3401-2155",
    "hours": {
      "standard": "7:30-20:30",
      "extended": null,
      "shortTime": null
    },
    "ageMin": 0,
    "ageMax": 2,
    "capacity": 13,
    "features": [
      "認証保育所",
      "延長保育",
      "少人数制"
    ],
    "hasGarden": false,
    "nearestStation": "六本木駅 徒歩5分",
    "website": "https://www.city.minato.tokyo.jp/shisetsu/gakkokyoiku/hoikuen/33.html",
    "lat": 35.6605,
    "lng": 139.7255,
    "operator": "私立",
    "notes": "東京都認証保育所。定員13名。0〜2歳児対象。営業時間7:30-20:30。"
  },
  {
    "slug": "cert-84",
    "name": "ニチイキッズさわやか麻布十番保育園",
    "type": "certified",
    "area": "azabu",
    "address": "港区麻布十番1-10-3",
    "phone": "03-3586-3887",
    "hours": {
      "standard": "8:00-22:00",
      "extended": null,
      "shortTime": null
    },
    "ageMin": 0,
    "ageMax": 5,
    "capacity": 30,
    "features": [
      "認証保育所",
      "延長保育",
      "少人数制"
    ],
    "hasGarden": false,
    "nearestStation": "麻布十番駅 徒歩2分",
    "website": "https://www.nichiikids.net/nursery/direct/sawayakaazabu/index.html",
    "lat": 35.654,
    "lng": 139.736,
    "operator": "私立",
    "notes": "東京都認証保育所。定員30名。営業時間8:00-22:00。"
  },
  {
    "slug": "cert-85",
    "name": "ポピンズナーサリースクール広尾",
    "type": "certified",
    "area": "azabu",
    "address": "港区南麻布5-1-11",
    "phone": "03-5475-2185",
    "hours": {
      "standard": "7:30-22:00",
      "extended": null,
      "shortTime": null
    },
    "ageMin": 0,
    "ageMax": 5,
    "capacity": 66,
    "features": [
      "認証保育所",
      "延長保育",
      "少人数制"
    ],
    "hasGarden": false,
    "nearestStation": "広尾駅 徒歩3分",
    "website": "https://www.poppins.co.jp/educare/room-search/hiroo/",
    "lat": 35.6508,
    "lng": 139.7215,
    "operator": "私立",
    "notes": "東京都認証保育所。定員66名。営業時間7:30-22:00。"
  },
  {
    "slug": "cert-86",
    "name": "ナーサリールーム",
    "type": "certified",
    "area": "azabu",
    "address": "港区南麻布5-6-8",
    "phone": "03-3473-8317",
    "hours": {
      "standard": "7:00-20:00",
      "extended": null,
      "shortTime": null
    },
    "ageMin": 0,
    "ageMax": 2,
    "capacity": 35,
    "features": [
      "認証保育所",
      "延長保育",
      "少人数制"
    ],
    "hasGarden": false,
    "nearestStation": "広尾駅 徒歩5分",
    "website": "https://www.city.minato.tokyo.jp/shisetsu/gakkokyoiku/hoikuen/ninsyo.html",
    "lat": 35.6495,
    "lng": 139.721,
    "operator": "私立",
    "notes": "東京都認証保育所。定員35名。0〜2歳児対象。営業時間7:00-20:00。"
  },
  {
    "slug": "cert-87",
    "name": "ゆらりん東麻布保育園",
    "type": "certified",
    "area": "azabu",
    "address": "港区東麻布1-26-2",
    "phone": "03-6426-5567",
    "hours": {
      "standard": "7:30-20:30",
      "extended": null,
      "shortTime": null
    },
    "ageMin": 0,
    "ageMax": 5,
    "capacity": 30,
    "features": [
      "認証保育所",
      "延長保育",
      "少人数制"
    ],
    "hasGarden": false,
    "nearestStation": "赤羽橋駅 徒歩3分 / 麻布十番駅 徒歩5分",
    "website": "https://hoiku.merhalsa.jp/yurarin-higashiazabu/",
    "lat": 35.6555,
    "lng": 139.74,
    "operator": "私立",
    "notes": "東京都認証保育所。定員30名。営業時間7:30-20:30。"
  },
  {
    "slug": "cert-88",
    "name": "ポピンズナーサリースクール赤坂",
    "type": "certified",
    "area": "akasaka-aoyama",
    "address": "港区赤坂1-8-1",
    "phone": "03-5545-5341",
    "hours": {
      "standard": "7:30-20:30",
      "extended": null,
      "shortTime": null
    },
    "ageMin": 0,
    "ageMax": 5,
    "capacity": 30,
    "features": [
      "認証保育所",
      "延長保育",
      "少人数制"
    ],
    "hasGarden": false,
    "nearestStation": "溜池山王駅 徒歩1分",
    "website": "https://www.poppins.co.jp/educare/room-search/akasaka/",
    "lat": 35.6735,
    "lng": 139.741,
    "operator": "私立",
    "notes": "東京都認証保育所。定員30名。営業時間7:30-20:30。"
  },
  {
    "slug": "cert-89",
    "name": "コンビプラザ白金台保育園",
    "type": "certified",
    "area": "takanawa-shirokane",
    "address": "港区白金台3-15-6",
    "phone": "03-5447-7600",
    "hours": {
      "standard": "7:30-20:30",
      "extended": null,
      "shortTime": null
    },
    "ageMin": 0,
    "ageMax": 5,
    "capacity": 39,
    "features": [
      "認証保育所",
      "延長保育",
      "少人数制"
    ],
    "hasGarden": false,
    "nearestStation": "白金台駅 徒歩2分",
    "website": "https://www.combiwith.co.jp/plaza/facilities/shiroganedai.html",
    "lat": 35.6388,
    "lng": 139.7242,
    "operator": "私立",
    "notes": "東京都認証保育所。定員39名。営業時間7:30-20:30。"
  },
  {
    "slug": "cert-90",
    "name": "ポピンズナーサリースクール白金台",
    "type": "certified",
    "area": "takanawa-shirokane",
    "address": "港区白金台4-8-16",
    "phone": "03-5789-2166",
    "hours": {
      "standard": "7:30-22:00",
      "extended": null,
      "shortTime": null
    },
    "ageMin": 0,
    "ageMax": 5,
    "capacity": 30,
    "features": [
      "認証保育所",
      "延長保育",
      "少人数制"
    ],
    "hasGarden": false,
    "nearestStation": "白金台駅 徒歩5分",
    "website": "https://www.poppins.co.jp/educare/room-search/shirokanedai/",
    "lat": 35.6382,
    "lng": 139.723,
    "operator": "私立",
    "notes": "東京都認証保育所。定員30名。営業時間7:30-22:00。"
  },
  {
    "slug": "cert-91",
    "name": "ニチイキッズさわやか白金高輪保育園",
    "type": "certified",
    "area": "takanawa-shirokane",
    "address": "港区白金1-25-25",
    "phone": "03-3441-6734",
    "hours": {
      "standard": "7:30-21:00",
      "extended": null,
      "shortTime": null
    },
    "ageMin": 0,
    "ageMax": 3,
    "capacity": 20,
    "features": [
      "認証保育所",
      "延長保育",
      "少人数制"
    ],
    "hasGarden": false,
    "nearestStation": "白金高輪駅 徒歩5分",
    "website": "https://www.nichiikids.net/nursery/direct/sawayakashirokane/index.html",
    "lat": 35.6425,
    "lng": 139.7295,
    "operator": "私立",
    "notes": "東京都認証保育所。定員20名。営業時間7:30-21:00。"
  },
  {
    "slug": "cert-92",
    "name": "ポピンズナーサリースクール高輪",
    "type": "certified",
    "area": "takanawa-shirokane",
    "address": "港区三田4-9-7",
    "phone": "03-5419-2115",
    "hours": {
      "standard": "7:30-22:00",
      "extended": null,
      "shortTime": null
    },
    "ageMin": 0,
    "ageMax": 5,
    "capacity": 36,
    "features": [
      "認証保育所",
      "延長保育",
      "少人数制"
    ],
    "hasGarden": false,
    "nearestStation": "白金高輪駅 徒歩5分 / 三田駅 徒歩8分",
    "website": "https://www.poppins.co.jp/educare/room-search/takanawa/",
    "lat": 35.644,
    "lng": 139.7375,
    "operator": "私立",
    "notes": "東京都認証保育所。定員36名。営業時間7:30-22:00。"
  },
  {
    "slug": "cert-93",
    "name": "アスクお台場保育園",
    "type": "certified",
    "area": "daiba-shibaura",
    "address": "港区台場2-2-3",
    "phone": "03-3599-2829",
    "hours": {
      "standard": "7:30-20:30",
      "extended": null,
      "shortTime": null
    },
    "ageMin": 0,
    "ageMax": 5,
    "capacity": 30,
    "features": [
      "認証保育所",
      "延長保育",
      "少人数制"
    ],
    "hasGarden": false,
    "nearestStation": "お台場海浜公園駅 徒歩5分",
    "website": "https://www.nihonhoiku.co.jp/blog/odaiba/",
    "lat": 35.6285,
    "lng": 139.774,
    "operator": "私立",
    "notes": "東京都認証保育所。定員30名。営業時間7:30-20:30。"
  },
  {
    "slug": "cert-94",
    "name": "アンジェリカ保育園芝浦園",
    "type": "certified",
    "area": "daiba-shibaura",
    "address": "港区芝浦4-22-2",
    "phone": "03-5439-4340",
    "hours": {
      "standard": "7:30-20:30",
      "extended": null,
      "shortTime": null
    },
    "ageMin": 0,
    "ageMax": 5,
    "capacity": 40,
    "features": [
      "認証保育所",
      "延長保育",
      "少人数制"
    ],
    "hasGarden": false,
    "nearestStation": "田町駅 徒歩15分",
    "website": "https://www.angelica-nsy.net/facilities/shibaura/",
    "lat": 35.6385,
    "lng": 139.754,
    "operator": "私立",
    "notes": "東京都認証保育所。定員40名。営業時間7:30-20:30。"
  },
  {
    "slug": "cert-95",
    "name": "ポピンズナーサリースクール芝浦",
    "type": "certified",
    "area": "daiba-shibaura",
    "address": "港区芝浦4-10-1",
    "phone": "03-5444-2120",
    "hours": {
      "standard": "7:30-22:00",
      "extended": null,
      "shortTime": null
    },
    "ageMin": 0,
    "ageMax": 5,
    "capacity": 34,
    "features": [
      "認証保育所",
      "延長保育",
      "少人数制"
    ],
    "hasGarden": false,
    "nearestStation": "田町駅 徒歩12分",
    "website": "https://www.city.minato.tokyo.jp/shisetsu/gakkokyoiku/hoikuen/45.html",
    "lat": 35.6395,
    "lng": 139.753,
    "operator": "私立",
    "notes": "東京都認証保育所。定員34名。営業時間7:30-22:00。"
  },
  {
    "slug": "cert-96",
    "name": "ニチイキッズさわやか港南保育園",
    "type": "certified",
    "area": "daiba-shibaura",
    "address": "港区港南4-2-5",
    "phone": "03-3471-9826",
    "hours": {
      "standard": "7:30-20:30",
      "extended": null,
      "shortTime": null
    },
    "ageMin": 0,
    "ageMax": 5,
    "capacity": 50,
    "features": [
      "認証保育所",
      "延長保育",
      "少人数制"
    ],
    "hasGarden": false,
    "nearestStation": "品川駅 徒歩12分",
    "website": "https://www.nichiikids.net/nursery/kounan/",
    "lat": 35.6262,
    "lng": 139.7448,
    "operator": "私立",
    "notes": "東京都認証保育所。定員50名。営業時間7:30-20:30。"
  },
  {
    "slug": "cert-97",
    "name": "アンジェリカ保育園品川園",
    "type": "certified",
    "area": "daiba-shibaura",
    "address": "港区港南2-3-13",
    "phone": "03-5781-9736",
    "hours": {
      "standard": "7:30-20:30",
      "extended": null,
      "shortTime": null
    },
    "ageMin": 0,
    "ageMax": 5,
    "capacity": 40,
    "features": [
      "認証保育所",
      "延長保育",
      "少人数制"
    ],
    "hasGarden": false,
    "nearestStation": "品川駅 徒歩5分",
    "website": "https://www.angelica-nsy.net/facilities/shinagawa/",
    "lat": 35.629,
    "lng": 139.742,
    "operator": "私立",
    "notes": "東京都認証保育所。定員40名。営業時間7:30-20:30。"
  }
]
